binaryrain_helper_cloud_aws/__init__.py
binaryrain_helper_cloud_aws/aws.py
binaryrain_helper_cloud_aws-0.0.11.dist-info/licenses/LICENSE
binaryrain_helper_cloud_aws-0.0.11.dist-info/METADATA
binaryrain_helper_cloud_aws-0.0.11.dist-info/WHEEL
binaryrain_helper_cloud_aws-0.0.11.dist-info/top_level.txt
binaryrain_helper_cloud_aws-0.0.11.dist-info/RECORD
