Metadata-Version: 2.4
Name: binaryrain-helper-cloud-aws
Version: 0.0.11
Summary: Aims to simplify and help with commonly used functions in the aws cloud data areas.
Author: Binary Rain, Marcel T.O
Project-URL: Homepage, https://binaryrain-net.github.io/Binary-Rain-Helper-Toolkit/
Keywords: binary rain,common,help,functions,aws
Classifier: Programming Language :: Python
Classifier: Programming Language :: Python :: 3
Requires-Python: >=3.10
License-File: LICENSE
Requires-Dist: aws-lambda-powertools[all]>=3.21.0
Requires-Dist: boto3>=1.40.64
Dynamic: license-file
